compox-2.1.0.dev1.dist-info/METADATA
compox-2.1.0.dev1.dist-info/WHEEL
compox-2.1.0.dev1.dist-info/entry_points.txt
compox-2.1.0.dev1.dist-info/licenses/LICENSE
compox-2.1.0.dev1.dist-info/licenses/NOTICE
compox-2.1.0.dev1.dist-info/licenses/THIRD_PARTY_LICENSES.txt
compox/__init__.py
compox/algorithm_debug.py
compox/algorithm_utils/AlgorithmConfigSchema.py
compox/algorithm_utils/AlgorithmDeployer.py
compox/algorithm_utils/AlgorithmManager.py
compox/algorithm_utils/BaseRunner.py
compox/algorithm_utils/Image2AlignmentRunner.py
compox/algorithm_utils/Image2EmbeddingRunner.py
compox/algorithm_utils/Image2ImageRunner.py
compox/algorithm_utils/Image2SegmentationRunner.py
compox/algorithm_utils/LocalDebugSession.py
compox/algorithm_utils/Segmentation2SegmentationRunner.py
compox/algorithm_utils/__init__.py
compox/algorithm_utils/deployment_utils.py
compox/algorithm_utils/io_schemas.py
compox/algorithm_utils/runner_context.py
compox/cli.py
compox/components/api_builder.py
compox/components/celery_builder.py
compox/components/db_connection_builder.py
compox/components/minio_wrapper.py
compox/components/server_builder.py
compox/config/server_settings.py
compox/database_connection/BaseConnection.py
compox/database_connection/InMemoryConnection.py
compox/database_connection/S3Connection.py
compox/database_connection/TempfileConnection.py
compox/database_connection/__init__.py
compox/database_connection/database_utils.py
compox/deploy_algorithms.py
compox/internal/CUDAMemoryManager.py
compox/internal/JobPOpen.py
compox/internal/ServerSystrayInterface.py
compox/internal/__init__.py
compox/internal/downloader.py
compox/internal/logging.py
compox/pydantic_models.py
compox/resources/compoxbackend.ico
compox/routers/__init__.py
compox/routers/algorithms_controller.py
compox/routers/execution_controller.py
compox/routers/execution_manager.py
compox/routers/file_controller.py
compox/routers/file_controller_v1.py
compox/routers/root.py
compox/run_server.py
compox/run_worker.py
compox/server_utils.py
compox/session/DataCache.py
compox/session/TaskSession.py
compox/session/__init__.py
compox/tasks/DebuggingTaskHandler.py
compox/tasks/TaskHandler.py
compox/tasks/__init__.py
compox/tasks/celery_task.py
compox/tasks/context_task_handler.py
compox-2.1.0.dev1.dist-info/RECORD
