Metadata-Version: 2.4
Name: compox
Version: 2.1.0.dev1
Author-Email: Jan Matula <jan.matula@tescan.com>, =?utf-8?q?Old=C5=99ich_Kodym?= <oldrich.kodym@tescan.com>
License-Expression: Apache-2.0 AND LicenseRef-Commons-Clause-1.0
License-File: LICENSE
License-File: NOTICE
License-File: THIRD_PARTY_LICENSES.txt
Requires-Python: >=3.10.0
Requires-Dist: fastapi>=0.100.1
Requires-Dist: boto3>=1.36.0
Requires-Dist: celery==5.3.1
Requires-Dist: uvicorn>=0.25.0
Requires-Dist: h5py>=3.9.0
Requires-Dist: numpy<2.0.0
Requires-Dist: natsort==8.4.0
Requires-Dist: pytest>=7.4.2
Requires-Dist: pydantic-settings>=2.0.3
Requires-Dist: python-minifier>=2.9.0
Requires-Dist: pystray>=0.19.5
Requires-Dist: pywin32>=306; platform_system == "Windows"
Requires-Dist: pyyaml>=6.0.2
Requires-Dist: toml>=0.10.2
Requires-Dist: flower>=2.0.1
Requires-Dist: python-multipart>=0.0.20
Requires-Dist: mangum>=0.19.0
Requires-Dist: requests==2.32.3
Requires-Dist: pycurl>=7.45.4
Requires-Dist: loguru>=0.7.3
Requires-Dist: typer>=0.16.0
Requires-Dist: pip>=25.2
Requires-Dist: build>=1.3.0
Requires-Dist: pdm-backend>=2.4.5
